{
    "name": "rbd-offline",
    "version": 3.5,
    "install_type": "local",
    "files":{
      "lvm_profile":"/etc/lvm/profile/docker-thinpool.profile",
      "docker_env_file":"/etc/goodrain/envs/docker.sh"
    },
    "rpms":{"docker":"gr-docker-engine-1.12.6-111.g1526e3f.el7.centos.x86_64"},
    "acpimg": ["rbd-db:3.4",
               "rbd-registry:2.3.1",
               "rbd-dalaran:3.4",
               "rbd-app-ui:3.4.2",
               "rbd-worker:3.4.2",
               "rbd-chaos:3.4.2",
               "prom/prometheus:v2.0.0",
               "rbd-slogger:3.4",
               "rbd-dns:3.4",
               "rbd-proxy:3.4",
               "rbd-mq:3.4.2",
               "rbd-repo:3.4",
               "rbd-eventlog:3.4.2",
               "rbd-lb:3.4.2",
               "rbd-api:3.4.2",
               "rbd-webcli:3.4.2",
               "rbd-entrance:3.4.2"
               ],
    "other_rbd_img":["kube-apiserver:v3.4.2",
                     "kube-controller-manager:v3.4.2",
                     "kube-scheduler:v3.4.2",
                     "etcd:v3.2.13",
                     "builder:latest",
                     "runner:latest",
                     "plugins:tcm_20180117175939",
                     "plugins:envoy_discover_service_20180117184912"
                   ],            
    "archiver":["archiver:latest",
                "archiver:gr-docker-utils",
                "archiver:gr-docker-compose",
                "archiver:domain"
                ],
    "other_img":["calico-node:v2.4.1",
                 "cfssl:latest",
                 "pause-amd64:3.0",
                 "adapter:3.4"
                 ],
    "compute_load_img":["rbd_proxy:3.4"],
    "default_rpms":["nfs-utils",
                    "wget",
                    "curl",
                    "epel-release",
                    "jq",
                    "tar",
                    "git",
                    "wget",
                    "perl",
                    "tree",
                    "curl",
                    "telnet",
                    "bind-utils",
                    "htop",
                    "dstat",
                    "net-tools",
                    "lsof",
                    "iproute",
                    "rsync",
                    "lvm2",
                    "bash-completion"]
    }